CHANGES.md
autoclick/__init__.py
autoclick/commands.py
autoclick/composites/__init__.py
autoclick/composites/library.py
autoclick/core.py
autoclick/parameters.py
autoclick/types/__init__.py
autoclick/types/library.py
autoclick/utils.py
autoclick/validations/__init__.py
autoclick/validations/library.py
autoclick-0.8.1.dist-info/entry_points.txt
autoclick-0.8.1.dist-info/LICENSE
autoclick-0.8.1.dist-info/WHEEL
autoclick-0.8.1.dist-info/METADATA
autoclick-0.8.1.dist-info/RECORD
