Metadata-Version: 2.1
Name: autoclick
Version: 0.8.1
Summary: Auto-generate Click-based CLIs from python3 type annotations.
Home-page: https://github.com/jdidion/autoclick
License: MIT
Author: John Didion
Author-email: github@didion.net
Requires-Python: >=3.6,<4.0
Classifier: Development Status :: 4 - Beta
Classifier: License :: OSI Approved :: MIT License
Classifier: Programming Language :: Python :: 3
Classifier: Programming Language :: Python :: 3.6
Classifier: Programming Language :: Python :: 3.7
Classifier: Programming Language :: Python :: 3.8
Requires-Dist: click (==7.0)
Requires-Dist: docparse
Project-URL: Repository, https://github.com/jdidion/autoclick.git
